boe_etl/__init__.py
boe_etl/__main__.py
boe_etl/cli.py
boe_etl/config.py
boe_etl/core.py
boe_etl/data_standardization.py
boe_etl/data_versioning.py
boe_etl/error_handling.py
boe_etl/etl_pipeline.py
boe_etl/fetch_and_parse.py
boe_etl/file_discovery.py
boe_etl/frontend.py
boe_etl/metadata.py
boe_etl/monitoring_dashboard.py
boe_etl/nlp.py
boe_etl/nlp_schema.py
boe_etl/pdf_parser.py
boe_etl/process_data_sources.py
boe_etl/progress_tracker.py
boe_etl/schema.py
boe_etl/schema_transformer.py
boe_etl/storage_config.py
boe_etl/text_cleaning.py
boe_etl/topic_modeling.py
boe_etl/topic_visualization.py
boe_etl/utils.py
boe_etl/version_tag_manager.py
boe_etl/version_tagging.py
boe_etl/version_visualization.py
boe_etl/config/etl_config.yaml
boe_etl/config/quarter_patterns.yml
boe_etl/data/fillers.json
boe_etl/data/seed_keywords.yml
boe_etl/parsers/__init__.py
boe_etl/parsers/base_parser.py
boe_etl/parsers/excel_parser.py
boe_etl/parsers/json_parser.py
boe_etl/parsers/pdf_parser.py
boe_etl/parsers/text_parser.py
boe_etl-1.0.0.dist-info/licenses/LICENSE
boe_etl-1.0.0.dist-info/METADATA
boe_etl-1.0.0.dist-info/WHEEL
boe_etl-1.0.0.dist-info/entry_points.txt
boe_etl-1.0.0.dist-info/top_level.txt
boe_etl-1.0.0.dist-info/RECORD
